LICENSE
MANIFEST.in
README.rst
setup.cfg
setup.py
django_zenmailbox.egg-info/PKG-INFO
django_zenmailbox.egg-info/SOURCES.txt
django_zenmailbox.egg-info/dependency_links.txt
django_zenmailbox.egg-info/requires.txt
django_zenmailbox.egg-info/top_level.txt
zenmailbox/__init__.py
zenmailbox/admin.py
zenmailbox/apps.py
zenmailbox/folder_set.py
zenmailbox/mailbox.py
zenmailbox/mailbox_manager.py
zenmailbox/models.py
zenmailbox/utils.py
zenmailbox/widgets.py
zenmailbox/migrations/0001_initial.py
zenmailbox/migrations/0002_attachment.py
zenmailbox/migrations/0003_mail_received_at.py
zenmailbox/migrations/0004_auto_20201113_0535.py
zenmailbox/migrations/0005_auto_20201113_0536.py
zenmailbox/migrations/0006_mail_subject.py
zenmailbox/migrations/0007_auto_20201229_1529.py
zenmailbox/migrations/0008_mailbox_initialized.py
zenmailbox/migrations/0009_auto_20210111_1144.py
zenmailbox/migrations/0010_auto_20210123_1500.py
zenmailbox/migrations/__init__.py
zenmailbox/templates/admin/zenmailbox/mail/change_form_object_tools.html
zenmailbox/templates/zenmailbox/messages_inline.html
zenmailbox/templates/zenmailbox/reply.html